Workbook

Sheet Cover & Assumptions
B2: Derivatives Overlay Program — Ashoka Capital Advisors (Simulated PMS Mandate)
B3: Quantitative model: options program, swap duration overlay, currency risk reversal, scenario stress test
B4: Equity sleeve position data (spot, IV, IV percentile) sourced from QuantsApp Pro+ live/EOD option-chain and IVR-IVP tools. Debt/FX/friction assumptions remain illustrative. Not investment advice.
B6: Key Assumption | C6: Value
B7: Mandate AUM (Rs Cr) | C7: 78
B8: Equity sleeve (Rs Cr) | C8: 68
B9: Debt sleeve (Rs Cr) | C9: 7
B10: USD/LRS sleeve (Rs Cr) | C10: 3
B11: Number of clients | C11: 14
B12: Equity beta to Nifty 50 | C12: 1.15
B13: Debt sleeve modified duration (yrs) | C13: 2.1
B14: Cost budget floor (bps p.a.) | C14: 40
B15: Cost budget ceiling (bps p.a.) | C15: 60
B16: Risk-free rate (annual) | C16: 0.068
B17: Blended dividend yield (annual) | C17: 0.012
B18: Collar tenor (days) | C18: 60
... B25: Monthly rollover drag (bps, mid) | C25: 10
B27: Source: QuantsApp Pro+ (Option Chain, IVR/IVP-H tools), captured 17-Jul-2026 close. Debt/FX/friction figures remain illustrative -- verify against live CCIL/RBI data and current NSE F&O circular before production use.

Sheet Collar Sleeve (Puts)
A1: Ticker | B1: Name | C1: Weight % AUM | D1: Spot | E1: IV (annual) | F1: Tenor (days) | G1: T (yrs) | H1: Put Strike* | I1: Call Strike* | J1: d1 (put) | K1: d2 (put) | L1: Put Premium | M1: d1 (call) | N1: d2 (call) | O1: Call Premium | P1: Net Premium (Rs) | Q1: Net Premium (% spot) | R1: Put Delta | S1: Call Delta | T1: Net Delta | U1: Notional (Rs Cr) | V1: Annual Cost (bps of AUM)
A2: SRF | B2: SRF Ltd - Specialty Chemicals (promoter-driven) | C2: 0.11 | D2: 2869.8 | E2: 0.3344 | F2: ='Cover & Assumptions'!$C$18 | G2: =F2/365 | H2: 2525.4 | I2: 3354.9 | J2: =(LN(D2/H2)+('Cover & Assumptions'!$C$16-'Cover & Assumptions'!$C$17+0.5*E2^2)*G2)/(E2*SQRT(G2)) | K2: =J2-E2*SQRT(G2) | L2: =H2*EXP(-'Cover & Assumptions'!$C$16*G2)*NORMSDIST(-K2)-D2*EXP(-'Cover & Assumptions'!$C$17*G2)*NORMSDIST(-J2) | M2: =(LN(D2/I2)+('Cover & Assumptions'!$C$16-'Cover & Assumptions'!$C$17+0.5*E2^2)*G2)/(E2*SQRT(G2)) | N2: =M2-E2*SQRT(G2) | O2: =D2*EXP(-'Cover & Assumptions'!$C$17*G2)*NORMSDIST(M2)-I2*EXP(-'Cover & Assumptions'!$C$16*G2)*NORMSDIST(N2) | P2: =O2-L2 | Q2: =P2/D2 | R2: =-EXP(-'Cover & Assumptions'!$C$17*G2)*NORMSDIST(-J2) | S2: =EXP(-'Cover & Assumptions'!$C$17*G2)*NORMSDIST(M2) | T2: =R2-S2 | U2: ='Cover & Assumptions'!$C$7*C2 | V2: =(-P2/D2+((L2+O2)/D2)*('Cover & Assumptions'!$C$23/10000)+(O2/D2)*'Cover & Assumptions'!$C$22+'Cover & Assumptions'!$C$25/10000)*(365/'Cover & Assumptions'!$C$18)*C2*10000
A3: BHARATFORG | B3: Bharat Forge - Promoter Industrial (Kalyani family) | C3: 0.095 | D3: 2197.5 | E3: 0.2898 | F3: ='Cover & Assumptions'!$C$18 | G3: =F3/365 | H3: 1933.8 | I3: 2564.2 | J3: =(LN(D3/H3)+('Cover & Assumptions'!$C$16-'Cover & Assumptions'!$C$17+0.5*E3^2)*G3)/(E3*SQRT(G3)) | K3: =J3-E3*SQRT(G3) | L3: =H3*EXP(-'Cover & Assumptions'!$C$16*G3)*NORMSDIST(-K3)-D3*EXP(-'Cover & Assumptions'!$C$17*G3)*NORMSDIST(-J3) | M3: =(LN(D3/I3)+('Cover & Assumptions'!$C$16-'Cover & Assumptions'!$C$17+0.5*E3^2)*G3)/(E3*SQRT(G3)) | N3: =M3-E3*SQRT(G3) | O3: =D3*EXP(-'Cover & Assumptions'!$C$17*G3)*NORMSDIST(M3)-I3*EXP(-'Cover & Assumptions'!$C$16*G3)*NORMSDIST(N3) | P3: =O3-L3 | Q3: =P3/D3 | R3: =-EXP(-'Cover & Assumptions'!$C$17*G3)*NORMSDIST(-J3) | S3: =EXP(-'Cover & Assumptions'!$C$17*G3)*NORMSDIST(M3) | T3: =R3-S3 | U3: ='Cover & Assumptions'!$C$7*C3 | V3: =(-P3/D3+((L3+O3)/D3)*('Cover & Assumptions'!$C$23/10000)+(O3/D3)*'Cover & Assumptions'!$C$22+'Cover & Assumptions'!$C$25/10000)*(365/'Cover & Assumptions'!$C$18)*C3*10000
A4: KALYANKJIL | B4: Kalyan Jewellers - Promoter Consumer/Retail | C4: 0.09 | D4: 573.75 | E4: 0.5823 | F4: ='Cover & Assumptions'!$C$18 | G4: =F4/365 | H4: 504.9 | I4: 678.3 | J4: =(LN(D4/H4)+('Cover & Assumptions'!$C$16-'Cover & Assumptions'!$C$17+0.5*E4^2)*G4)/(E4*SQRT(G4)) | K4: =J4-E4*SQRT(G4) | L4: =H4*EXP(-'Cover & Assumptions'!$C$16*G4)*NORMSDIST(-K4)-D4*EXP(-'Cover & Assumptions'!$C$17*G4)*NORMSDIST(-J4) | M4: =(LN(D4/I4)+('Cover & Assumptions'!$C$16-'Cover & Assumptions'!$C$17+0.5*E4^2)*G4)/(E4*SQRT(G4)) | N4: =M4-E4*SQRT(G4) | O4: =D4*EXP(-'Cover & Assumptions'!$C$17*G4)*NORMSDIST(M4)-I4*EXP(-'Cover & Assumptions'!$C$16*G4)*NORMSDIST(N4) | P4: =O4-L4 | Q4: =P4/D4 | R4: =-EXP(-'Cover & Assumptions'!$C$17*G4)*NORMSDIST(-J4) | S4: =EXP(-'Cover & Assumptions'!$C$17*G4)*NORMSDIST(M4) | T4: =R4-S4 | U4: ='Cover & Assumptions'!$C$7*C4 | V4: =(-P4/D4+((L4+O4)/D4)*('Cover & Assumptions'!$C$23/10000)+(O4/D4)*'Cover & Assumptions'!$C$22+'Cover & Assumptions'!$C$25/10000)*(365/'Cover & Assumptions'!$C$18)*C4*10000
A5: POLYCAB | B5: Polycab India - Promoter Electricals (Jaisinghani family) | C5: 0.085 | D5: 8862.5 | E5: 0.2802 | F5: ='Cover & Assumptions'!$C$18 | G5: =F5/365 | H5: 7799 | I5: 10337.3 | J5: =(LN(D5/H5)+('Cover & Assumptions'!$C$16-'Cover & Assumptions'!$C$17+0.5*E5^2)*G5)/(E5*SQRT(G5)) | K5: =J5-E5*SQRT(G5) | L5: =H5*EXP(-'Cover & Assumptions'!$C$16*G5)*NORMSDIST(-K5)-D5*EXP(-'Cover & Assumptions'!$C$17*G5)*NORMSDIST(-J5) | M5: =(LN(D5/I5)+('Cover & Assumptions'!$C$16-'Cover & Assumptions'!$C$17+0.5*E5^2)*G5)/(E5*SQRT(G5)) | N5: =M5-E5*SQRT(G5) | O5: =D5*EXP(-'Cover & Assumptions'!$C$17*G5)*NORMSDIST(M5)-I5*EXP(-'Cover & Assumptions'!$C$16*G5)*NORMSDIST(N5) | P5: =O5-L5 | Q5: =P5/D5 | R5: =-EXP(-'Cover & Assumptions'!$C$17*G5)*NORMSDIST(-J5) | S5: =EXP(-'Cover & Assumptions'!$C$17*G5)*NORMSDIST(M5) | T5: =R5-S5 | U5: ='Cover & Assumptions'!$C$7*C5 | V5: =(-P5/D5+((L5+O5)/D5)*('Cover & Assumptions'!$C$23/10000)+(O5/D5)*'Cover & Assumptions'!$C$22+'Cover & Assumptions'!$C$25/10000)*(365/'Cover & Assumptions'!$C$18)*C5*10000
B7: TOTAL / Weighted | C7: =SUM(C2:C5) | U7: =SUM(U2:U5) | V7: =SUM(V2:V5)
B9: * Put/Call strikes solved externally via scipy.optimize (Black-Scholes zero-cost / min-premium root-find, min 12% protection floor) — see src/bs_engine.py::solve_min_premium_collar(). Spot/IV inputs sourced from QuantsApp Pro+ Option Chain. Re-run src/overlay_model.py and paste updated strikes here if spot/IV inputs change.

Sheet Covered Call Sleeve
A1: Ticker | B1: Name | C1: Weight % AUM | D1: Spot | E1: IV (annual) | F1: Tenor (days) | G1: T (yrs) | H1: OTM %* | I1: Call Strike | J1: d1 | K1: d2 | L1: Call Premium | M1: Premium % Spot | N1: Call Delta | O1: Annual Income (bps of AUM)
A2: HDFCBANK | B2: HDFC Bank - Large Private Bank | C2: 0.06 | D2: 819.9 | E2: 0.245 | F2: ='Cover & Assumptions'!$C$20 | G2: =F2/365 | H2: ='Cover & Assumptions'!$C$21 | I2: =D2*(1+H2) | J2: =(LN(D2/I2)+('Cover & Assumptions'!$C$16-'Cover & Assumptions'!$C$17+0.5*E2^2)*G2)/(E2*SQRT(G2)) | K2: =J2-E2*SQRT(G2) | L2: =D2*EXP(-'Cover & Assumptions'!$C$17*G2)*NORMSDIST(J2)-I2*EXP(-'Cover & Assumptions'!$C$16*G2)*NORMSDIST(K2) | M2: =L2/D2 | N2: =EXP(-'Cover & Assumptions'!$C$17*G2)*NORMSDIST(J2) | O2: =(L2/D2)*(1-'Cover & Assumptions'!$C$24/10000-'Cover & Assumptions'!$C$22)*(365/'Cover & Assumptions'!$C$20)*C2*10000
A3: ICICIBANK | B3: ICICI Bank - Large Private Bank | C3: 0.055 | D3: 1449.1 | E3: 0.2549 | F3: ='Cover & Assumptions'!$C$20 | G3: =F3/365 | H3: ='Cover & Assumptions'!$C$21 | I3: =D3*(1+H3) | J3: =(LN(D3/I3)+('Cover & Assumptions'!$C$16-'Cover & Assumptions'!$C$17+0.5*E3^2)*G3)/(E3*SQRT(G3)) | K3: =J3-E3*SQRT(G3) | L3: =D3*EXP(-'Cover & Assumptions'!$C$17*G3)*NORMSDIST(J3)-I3*EXP(-'Cover & Assumptions'!$C$16*G3)*NORMSDIST(K3) | M3: =L3/D3 | N3: =EXP(-'Cover & Assumptions'!$C$17*G3)*NORMSDIST(J3) | O3: =(L3/D3)*(1-'Cover & Assumptions'!$C$24/10000-'Cover & Assumptions'!$C$22)*(365/'Cover & Assumptions'!$C$20)*C3*10000
A4: INFY | B4: Infosys - Large IT | C4: 0.05 | D4: 1090 | E4: 0.3372 | F4: ='Cover & Assumptions'!$C$20 | G4: =F4/365 | H4: ='Cover & Assumptions'!$C$21 | I4: =D4*(1+H4) | J4: =(LN(D4/I4)+('Cover & Assumptions'!$C$16-'Cover & Assumptions'!$C$17+0.5*E4^2)*G4)/(E4*SQRT(G4)) | K4: =J4-E4*SQRT(G4) | L4: =D4*EXP(-'Cover & Assumptions'!$C$17*G4)*NORMSDIST(J4)-I4*EXP(-'Cover & Assumptions'!$C$16*G4)*NORMSDIST(K4) | M4: =L4/D4 | N4: =EXP(-'Cover & Assumptions'!$C$17*G4)*NORMSDIST(J4) | O4: =(L4/D4)*(1-'Cover & Assumptions'!$C$24/10000-'Cover & Assumptions'!$C$22)*(365/'Cover & Assumptions'!$C$20)*C4*10000
A5: LT | B5: L&T - Large Cap Engineering | C5: 0.045 | D5: 3843.6 | E5: 0.2433 | F5: ='Cover & Assumptions'!$C$20 | G5: =F5/365 | H5: ='Cover & Assumptions'!$C$21 | I5: =D5*(1+H5) | J5: =(LN(D5/I5)+('Cover & Assumptions'!$C$16-'Cover & Assumptions'!$C$17+0.5*E5^2)*G5)/(E5*SQRT(G5)) | K5: =J5-E5*SQRT(G5) | L5: =D5*EXP(-'Cover & Assumptions'!$C$17*G5)*NORMSDIST(J5)-I5*EXP(-'Cover & Assumptions'!$C$16*G5)*NORMSDIST(K5) | M5: =L5/D5 | N5: =EXP(-'Cover & Assumptions'!$C$17*G5)*NORMSDIST(J5) | O5: =(L5/D5)*(1-'Cover & Assumptions'!$C$24/10000-'Cover & Assumptions'!$C$22)*(365/'Cover & Assumptions'!$C$20)*C5*10000
A6: HINDUNILVR | B6: HUL - Large Cap FMCG | C6: 0.04 | D6: 2150.2 | E6: 0.2207 | F6: ='Cover & Assumptions'!$C$20 | G6: =F6/365 | H6: ='Cover & Assumptions'!$C$21 | I6: =D6*(1+H6) | J6: =(LN(D6/I6)+('Cover & Assumptions'!$C$16-'Cover & Assumptions'!$C$17+0.5*E6^2)*G6)/(E6*SQRT(G6)) | K6: =J6-E6*SQRT(G6) | L6: =D6*EXP(-'Cover & Assumptions'!$C$17*G6)*NORMSDIST(J6)-I6*EXP(-'Cover & Assumptions'!$C$16*G6)*NORMSDIST(K6) | M6: =L6/D6 | N6: =EXP(-'Cover & Assumptions'!$C$17*G6)*NORMSDIST(J6) | O6: =(L6/D6)*(1-'Cover & Assumptions'!$C$24/10000-'Cover & Assumptions'!$C$22)*(365/'Cover & Assumptions'!$C$20)*C6*10000
A7: TITAN | B7: Titan - Large Cap Consumer | C7: 0.04 | D7: 4636.3 | E7: 0.1998 | F7: ='Cover & Assumptions'!$C$20 | G7: =F7/365 | H7: ='Cover & Assumptions'!$C$21 | I7: =D7*(1+H7) | J7: =(LN(D7/I7)+('Cover & Assumptions'!$C$16-'Cover & Assumptions'!$C$17+0.5*E7^2)*G7)/(E7*SQRT(G7)) | K7: =J7-E7*SQRT(G7) | L7: =D7*EXP(-'Cover & Assumptions'!$C$17*G7)*NORMSDIST(J7)-I7*EXP(-'Cover & Assumptions'!$C$16*G7)*NORMSDIST(K7) | M7: =L7/D7 | N7: =EXP(-'Cover & Assumptions'!$C$17*G7)*NORMSDIST(J7) | O7: =(L7/D7)*(1-'Cover & Assumptions'!$C$24/10000-'Cover & Assumptions'!$C$22)*(365/'Cover & Assumptions'!$C$20)*C7*10000
B9: TOTAL | C9: =SUM(C2:C7) | O9: =SUM(O2:O7)
B11: * OTM% and tenor deliberately wide/infrequent (15% OTM, semi-annual) vs a tighter monthly-6%-OTM design, to satisfy the client objective of 'modest yield without capping upside materially' — see report Methodology section 3.

Sheet Program Cost Summary
B2: Overlay Program — Net Cost / Income Summary (bps of Total AUM, annualised)
B4: Gross protective put/collar cost | C4: ='Collar Sleeve (Puts)'!$V$7
B5: Gross covered call income | C5: ='Covered Call Sleeve'!$O$9
B6: Net program cost / (credit) | C6: =C4-C5
B7: Cost budget floor (bps) | C7: ='Cover & Assumptions'!$C$14
B8: Cost budget ceiling (bps) | C8: ='Cover & Assumptions'!$C$15
B9: Budget headroom (ceiling - gross put/collar cost) | C9: =C8-C4
B10: Within budget? | C10: =IF(C4<=C8,"YES - within budget","NO - exceeds budget")

Sheet IV Percentile Tracker
A1: Ticker | B1: Current IV | C1: 90D IV Low | D1: 90D IV High | E1: IV Percentile (90D) | F1: Hedge Trigger
A2: SRF | B2: 0.334 | C2: 0.21 | D2: 0.42 | E2: =(B2-C2)/(D2-C2) | F2: =IF(E2<=33.3%,"HEDGE NOW (cheap)",IF(E2<=66.7%,"WATCH","EXPENSIVE - defer"))
A3: BHARATFORG | B3: 0.29 | C3: 0.26 | D3: 0.41 | E3: =(B3-C3)/(D3-C3) | F3: =IF(E3<=33.3%,"HEDGE NOW (cheap)",IF(E3<=66.7%,"WATCH","EXPENSIVE - defer"))
A4: KALYANKJIL | B4: 0.582 | C4: 0.37 | D4: 0.72 | E4: =(B4-C4)/(D4-C4) | F4: =IF(E4<=33.3%,"HEDGE NOW (cheap)",IF(E4<=66.7%,"WATCH","EXPENSIVE - defer"))
A5: POLYCAB | B5: 0.28 | C5: 0.26 | D5: 0.39 | E5: =(B5-C5)/(D5-C5) | F5: =IF(E5<=33.3%,"HEDGE NOW (cheap)",IF(E5<=66.7%,"WATCH","EXPENSIVE - defer"))
A6: HDFCBANK | B6: 0.245 | C6: 0.2 | D6: 0.33 | E6: =(B6-C6)/(D6-C6) | F6: =IF(E6<=33.3%,"HEDGE NOW (cheap)",IF(E6<=66.7%,"WATCH","EXPENSIVE - defer"))
A7: ICICIBANK | B7: 0.255 | C7: 0.195 | D7: 0.3 | E7: =(B7-C7)/(D7-C7) | F7: =IF(E7<=33.3%,"HEDGE NOW (cheap)",IF(E7<=66.7%,"WATCH","EXPENSIVE - defer"))
A8: INFY | B8: 0.337 | C8: 0.3 | D8: 0.39 | E8: =(B8-C8)/(D8-C8) | F8: =IF(E8<=33.3%,"HEDGE NOW (cheap)",IF(E8<=66.7%,"WATCH","EXPENSIVE - defer"))
A9: LT | B9: 0.243 | C9: 0.205 | D9: 0.318 | E9: =(B9-C9)/(D9-C9) | F9: =IF(E9<=33.3%,"HEDGE NOW (cheap)",IF(E9<=66.7%,"WATCH","EXPENSIVE - defer"))
A10: HINDUNILVR | B10: 0.221 | C10: 0.209 | D10: 0.259 | E10: =(B10-C10)/(D10-C10) | F10: =IF(E10<=33.3%,"HEDGE NOW (cheap)",IF(E10<=66.7%,"WATCH","EXPENSIVE - defer"))
A11: TITAN | B11: 0.2 | C11: 0.2 | D11: 0.316 | E11: =(B11-C11)/(D11-C11) | F11: =IF(E11<=33.3%,"HEDGE NOW (cheap)",IF(E11<=66.7%,"WATCH","EXPENSIVE - defer"))
A13: Note: Current IV and 90D low/high bands sourced from QuantsApp Pro+ IVR/IVP-H tool (captured 17-Jul-2026 close). 90-day series itself uses a bounded synthetic path anchored to these real endpoints (src/bs_engine.py::synthetic_iv_series) for the chart -- replace with a full daily QuantsApp/NSE IV export for exact day-by-day history.

Sheet Scenario Analysis
B2: Portfolio Value Under Market Scenarios — Hedged vs Unhedged
A4: Scenario | B4: Type | C4: Unhedged Return % | D4: Hedged Return % | E4: Drawdown Reduction (bps) | F4: Protection Efficiency %
A5: -10% instantaneous market move | B5: hypothetical | C5: -0.115 | D5: -0.0973 | E5: 177 | F5: 0.154
A6: -20% instantaneous market move | B6: hypothetical | C6: -0.23 | D6: -0.1705 | E6: 595 | F6: 0.259
A7: +15% instantaneous market move | B7: hypothetical | C7: 0.1725 | D7: 0.1831
A8: Feb-Mar 2020 COVID Crash | B8: historical_proxy | C8: -0.437 | D8: -0.3482 | E8: 888 | F8: 0.203
A9: 2022 Rate-Hike Correction | B9: historical_proxy | C9: -0.184 | D9: -0.1419 | E9: 421 | F9: 0.229
A10: 2024 Pre-Election Volatility Spike | B10: historical_proxy | C10: -0.1035 | D10: -0.0858 | E10: 177 | F10: 0.171
A12: Note: portfolio-level approximation using AUM-weighted sleeve betas and actual collar/covered-call strike distances; not a full multi-asset Monte Carlo. See src/overlay_model.py::portfolio_value_under_shock().

Sheet Swap & Currency Overlay
B2: Debt Sleeve — Swap-Based Duration Overlay
B4: Debt sleeve (Rs Cr) | C4: 7
B5: Current modified duration (yrs) | C5: 2.1
B6: Target duration shift (yrs) | C6: 0.75
B7: Approx. swap notional required (Rs Cr) | C7: =C4*(C6/C5)
B8: Cost avoidance vs physical bond trade (Rs Lakh) | C8: 4.2
B9: Capital gains avoided (Rs Lakh) | C9: 18
B11: Counterparty: OTC, CCIL-cleared (distinct risk profile vs exchange-cleared equity F&O — see Risk Framework). Duration/cost-avoidance figures remain illustrative (bond-desk data not sourced from QuantsApp).
B14: Currency Overlay — USD/LRS Risk Reversal (Collar)
B16: Total USD/LRS allocation (Rs Cr) | C16: 3
B17: Target hedge ratio | C17: 0.5
B18: Hedge notional (Rs Cr) | C18: =C16*C17
B19: Structure | C19: Risk reversal (collar): long USD put / short USD call
B20: Tenor (days) | C20: 180
B21: USDINR Spot | C21: 86.5
B22: USDINR annualised vol | C22: 0.065
B23: Put strike (USDINR) | C23: 84.77
B24: Call strike (USDINR) | C24: 91.69
B25: Put premium (USDINR) | C25: 0.226
B26: Call premium (USDINR) | C26: 0.74
B27: Net premium (USDINR) | C27: =C26-C25

Sheet Risk Framework
B2: Margin Stress Test & Liquidity Contingency
B4: Baseline margin (Rs Cr) | C4: 1.8
B5: Margin stress move (Nifty, single day) | C5: 0.07
B6: Margin stress increase (%) | C6: 0.65
B7: Stressed margin requirement (Rs Cr) | C7: =C4*(1+C6)
B8: Minimum collateral buffer policy (Rs Cr) | C8: 3.5
B9: Buffer over stressed requirement (%) | C9: =C8/C7-1
B10: Redemption stress scenario (% AUM) | C10: 0.2
B11: Redemption stress scenario (Rs Cr) | C11: ='Cover & Assumptions'!$C$7*C10
B13: Escalation Triggers
B14: - Hedge cost exceeding 60bps budget by >20% in any quarter -> mandatory IC review
B15: - Margin utilization exceeding 70% of posted collateral -> immediate de-risking of options book
B16: - Single-name option liquidity score (OI/ADV) below desk threshold -> mandatory switch to index-proxy hedge
B17: - Portfolio tracking error vs Nifty 500 exceeding 8% band (incl. overlay effects) -> review and rebalance
